secken.py
setup.py
secken_api.egg-info/PKG-INFO
secken_api.egg-info/SOURCES.txt
secken_api.egg-info/dependency_links.txt
secken_api.egg-info/top_level.txt