Metadata-Version: 1.0
Name: secken-api
Version: 2.5
Summary: 洋葱官方python sdk
Home-page: http://www.secken.com
Author: Secken
Author-email: UNKNOWN
License: LGPL
Platform: UNKNOWN
